[
  {
    "Id": "418288",
    "ThreadId": "205011",
    "Html": "<p>If I am building a WPF app only, should I be using Prism v1 or v2?&nbsp; If v1, can you briefly explain why?</p>\r\n<p>Tks much.</p>",
    "PostedDate": "2010-03-15T08:55:44.673-07:00",
    "UserRole": null,
    "MarkedAsAnswerDate": null
  },
  {
    "Id": "419288",
    "ThreadId": "205011",
    "Html": "<p>Hi,</p>\r\n<p>I would recommend using Prism-v2, as some new features were introduced in v2  aside from support for Silverlight; and nonetheless, it is designed to work with  WPF.</p>\r\n<p id=d396d350-1344-012d-716b-123139061101>You can  check <a href=\"http://msdn.microsoft.com/en-us/library/dd490816.aspx\">this  document</a> to see some of those new features, if you are interested.</p>\r\n<p id=d396e1f0-1344-012d-716c-123139061101>I hope you find this helpful.</p>\r\n<p id=d396f080-1344-012d-716d-123139061101>Guido Leandro Maliandi <br><a href=\"http://blogs.southworks.net/gmaliandi\">http://blogs.southworks.net/gmaliandi</a></p>\r\n<p>&nbsp;</p>",
    "PostedDate": "2010-03-17T09:26:34.263-07:00",
    "UserRole": null,
    "MarkedAsAnswerDate": null
  },
  {
    "Id": "419295",
    "ThreadId": "205011",
    "Html": "<p>Thanks Guido.&nbsp; I thought this was the case but was just looking for confirmation that v2 was not for Silverlight only, etc.</p>\r\n<p>Tks.</p>",
    "PostedDate": "2010-03-17T09:31:21.433-07:00",
    "UserRole": null,
    "MarkedAsAnswerDate": null
  }
]