[
  {
    "Id": "280020",
    "ThreadId": "81563",
    "Html": "<p>Hi,</p>\r\n<p>I'm using Silverlight 3 - Prism 2 - WCF Ria Services.</p>\r\n<p>I defined&nbsp;a domain service / entity framework class in the web application, and I use the same domain service in multiple prism modules.</p>\r\n<p>When I'm trying to query de database, for instance</p>\r\n<p>&nbsp;&nbsp; myContext.Load&lt;myEntity&gt;(myContext.GetMyEntities(), true).AllEntities;&nbsp;&nbsp; (I tryed every possible syntax, I think it isn't the problem)</p>\r\n<p>I receive an error message saying that myWebApp.myEntity is defined in multiples modules.</p>\r\n<p>What I'm doing wrong?&nbsp; Can't I use the same domain service in multiples modules?</p>\r\n<p>Thanks in advance</p>\r\n<p>Marcos</p>",
    "PostedDate": "2010-01-21T05:55:32.473-08:00",
    "UserRole": null,
    "MarkedAsAnswerDate": null
  }
]